threedgame/__init__.py
threedgame/core.py
threedgame-2.1.0.dist-info/LICENSE
threedgame-2.1.0.dist-info/METADATA
threedgame-2.1.0.dist-info/WHEEL
threedgame-2.1.0.dist-info/top_level.txt
threedgame-2.1.0.dist-info/RECORD
