Metadata-Version: 2.2
Name: threedgame
Version: 2.1.0
Summary: A brief description of your library
Home-page: https://github.com/feng/myfeng
Author: hhsdn
Author-email: empiresoft@qq.com
Classifier: Programming Language :: Python :: 3
Classifier: License :: OSI Approved :: MIT License
Classifier: Operating System :: OS Independent
Requires-Python: >=3.6
License-File: LICENSE
Requires-Dist: ursina>=0.4.0
Dynamic: author
Dynamic: author-email
Dynamic: classifier
Dynamic: description
Dynamic: description-content-type
Dynamic: home-page
Dynamic: requires-dist
Dynamic: requires-python
Dynamic: summary
